<?xml version="1.0" encoding="utf-8" ?>
<dwsync>
<file name="brits_abroad_465x351.jpg" server="sftp.york.ac.uk" local="130300293906339420" remote="130300297940000000" />
<file name="nursing_patients_230x173.jpg" server="sftp.york.ac.uk" local="130300295763279560" remote="130300297940000000" />
<file name="scriptwriting_award_230x351.jpg" server="sftp.york.ac.uk" local="130300295323367110" remote="130300297940000000" />
<file name="who_cghh_230x173.jpg" server="sftp.york.ac.uk" local="130300296164190530" remote="130300297950000000" />
<file name="caves_465x351.jpg" server="sftp.york.ac.uk" local="130305558050000000" remote="130305558050000000" />
<file name="music_video_230x173.jpg" server="sftp.york.ac.uk" local="130305552071633465" remote="130305558050000000" />
<file name="scopus_230x173.jpg" server="sftp.york.ac.uk" local="130305552257412041" remote="130305558050000000" />
<file name="yccsa_event_230x351.jpg" server="sftp.york.ac.uk" local="130305557633649611" remote="130305558060000000" />
<file name="cnap-research-grants.jpg" server="sftp.york.ac.uk" local="130311683803085387" remote="130311686290000000" />
<file name="salters-chair-bennett.jpg" server="sftp.york.ac.uk" local="130311684712836353" remote="130311686290000000" />
<file name="stained-glass.jpg" server="sftp.york.ac.uk" local="130311685107645830" remote="130311686290000000" />
<file name="york-talk.png" server="sftp.york.ac.uk" local="130311684372242297" remote="130311686290000000" />
<file name="salters-chair.jpg" server="sftp.york.ac.uk" local="130312535438393625" remote="130312535860000000" />
<file name="careers-key-message.png" server="sftp.york.ac.uk" local="130317643949746060" remote="130318492850000000" />
<file name="turkey.jpg" server="sftp.york.ac.uk" local="130318543110127227" remote="130318543780000000" />
<file name="yccsa_whales.jpg" server="sftp.york.ac.uk" local="130318543377043916" remote="130318543780000000" />
<file name="cone-snails.jpg" server="sftp.york.ac.uk" local="130322768284926249" remote="130322768750000000" />
</dwsync>